ipfsapi/__init__.py
ipfsapi/client.py
ipfsapi/encoding.py
ipfsapi/exceptions.py
ipfsapi/http.py
ipfsapi/multipart.py
ipfsapi/utils.py
ipfsapi/version.py
ipfsapi-0.4.3.dist-info/LICENSE
ipfsapi-0.4.3.dist-info/WHEEL
ipfsapi-0.4.3.dist-info/METADATA
ipfsapi-0.4.3.dist-info/RECORD
