Metadata-Version: 1.1
Name: ipfsapi
Version: 0.4.3
Summary: Python IPFS API client library
Home-page: https://github.com/ipfs/py-ipfs-api
Author: py-ipfs-api team
Author-email: 
